sha_loop.cpython-36m-darwin.so
shaloop-0.0.1.dist-info/LICENSE
shaloop-0.0.1.dist-info/METADATA
shaloop-0.0.1.dist-info/WHEEL
shaloop-0.0.1.dist-info/top_level.txt
shaloop-0.0.1.dist-info/RECORD
